MANIFEST.in
README.md
setup.py
lib/__init__.py
lib/plugins.py
lib/scrape.py
tests/__init__.py
tests/test_scrape.py
uip_scrape.egg-info/PKG-INFO
uip_scrape.egg-info/SOURCES.txt
uip_scrape.egg-info/dependency_links.txt
uip_scrape.egg-info/top_level.txt