Metadata-Version: 1.1
Name: uip-scrape
Version: 0.0.3
Summary: A library to write image scraping plugins andrunning them to return a list of image_links
Home-page: UNKNOWN
Author: Abhay Raizada
Author-email: toabhayraizada@gmail.com
License: MIT
Keywords: python image scraping library
Platform: UNKNOWN
Classifier: Development Status :: 3 - Alpha
Classifier: Topic :: Utilities
Classifier: License :: OSI Approved :: MIT License
